karrio/server/documents/__init__.py
karrio/server/documents/admin.py
karrio/server/documents/apps.py
karrio/server/documents/filters.py
karrio/server/documents/generator.py
karrio/server/documents/models.py
karrio/server/documents/signals.py
karrio/server/documents/tests.py
karrio/server/documents/urls.py
karrio/server/documents/utils.py
karrio/server/documents/migrations/0001_initial.py
karrio/server/documents/migrations/0002_alter_documenttemplate_related_objects.py
karrio/server/documents/migrations/0003_rename_related_objects_documenttemplate_related_object.py
karrio/server/documents/migrations/0004_documenttemplate_active.py
karrio/server/documents/migrations/0005_alter_documenttemplate_description_and_more.py
karrio/server/documents/migrations/0006_documenttemplate_metadata.py
karrio/server/documents/migrations/0007_alter_documenttemplate_related_object.py
karrio/server/documents/migrations/0008_documenttemplate_options.py
karrio/server/documents/migrations/__init__.py
karrio/server/documents/serializers/__init__.py
karrio/server/documents/serializers/base.py
karrio/server/documents/serializers/documents.py
karrio/server/documents/tests/__init__.py
karrio/server/documents/tests/test_generator.py
karrio/server/documents/tests/test_templates.py
karrio/server/documents/views/__init__.py
karrio/server/documents/views/printers.py
karrio/server/documents/views/templates.py
karrio/server/graph/schemas/__init__.py
karrio/server/graph/schemas/documents/__init__.py
karrio/server/graph/schemas/documents/inputs.py
karrio/server/graph/schemas/documents/mutations.py
karrio/server/graph/schemas/documents/types.py
karrio_server_documents-2026.1.4.dist-info/METADATA
karrio_server_documents-2026.1.4.dist-info/WHEEL
karrio_server_documents-2026.1.4.dist-info/top_level.txt
karrio_server_documents-2026.1.4.dist-info/RECORD
